ConsoleMasterPy/__init__.py
ConsoleMasterPy/console_master.py
ConsoleMasterPy-1.0.7.1.dist-info/METADATA
ConsoleMasterPy-1.0.7.1.dist-info/WHEEL
ConsoleMasterPy-1.0.7.1.dist-info/top_level.txt
ConsoleMasterPy-1.0.7.1.dist-info/RECORD
