Metadata-Version: 2.1
Name: ConsoleMasterPy
Version: 1.0.7.1
Summary: Console/Terminal functionality
Author: Ronchetti Ezequiel Nicolás
Author-email: RonchettiEzequielNicolas@hotmail.com
Classifier: Programming Language :: Python :: 3
Classifier: License :: OSI Approved :: MIT License
Classifier: Operating System :: OS Independent
Requires-Python: >=3.6
Requires-Dist: cursor >=1.3.5
Requires-Dist: sty >=1.0.4
